tamar_community_sdk/__init__.py
tamar_community_sdk/exceptions.py
tamar_community_sdk/py.typed
tamar_community_sdk/sdk.py
tamar_community_sdk/types.py
tamar_community_sdk-2.0.19.dist-info/METADATA
tamar_community_sdk-2.0.19.dist-info/WHEEL
tamar_community_sdk-2.0.19.dist-info/top_level.txt
tamar_community_sdk-2.0.19.dist-info/RECORD
