Metadata-Version: 2.4
Name: tamar-community-sdk
Version: 2.0.19
Summary: Tamar Community SDK for Python - 支持文件上传、HLS视频流、文件管理
Author-email: Tamar Team <dev@tamar.com>
License: MIT
Project-URL: Homepage, https://github.com/tamar/tamar-community-sdk-python
Keywords: upload,oss,multipart,async,hls,streaming
Classifier: Development Status :: 4 - Beta
Classifier: Intended Audience :: Developers
Classifier: License :: OSI Approved :: MIT License
Classifier: Programming Language :: Python :: 3
Classifier: Programming Language :: Python :: 3.9
Classifier: Programming Language :: Python :: 3.10
Classifier: Programming Language :: Python :: 3.11
Classifier: Programming Language :: Python :: 3.12
Classifier: Framework :: AsyncIO
Requires-Python: >=3.9
Requires-Dist: aiohttp>=3.8.0
Requires-Dist: aiofiles>=23.0.0
Provides-Extra: dev
Requires-Dist: pytest>=7.0.0; extra == "dev"
Requires-Dist: pytest-asyncio>=0.21.0; extra == "dev"
